tpds/__init__.py
tpds/schema/__init__.py
tpds/schema/data/cryptoauth/ECC204_TA010_Config_1.0.xsd
tpds/schema/data/cryptoauth/ECC204_TA010_Config_1.1.xsd
tpds/schema/data/cryptoauth/ECC204_TA010_Config_1.2.xsd
tpds/schema/data/cryptoauth/SHA104_Config_1.0.xsd
tpds/schema/data/cryptoauth/SHA105_Config_1.0.xsd
tpds/schema/data/generic/Provisioning_Config_1.0.xsd
tpds/schema/data/generic/Provisioning_Config_1.1.xsd
tpds/schema/models/__init__.py
tpds/schema/models/common/__init__.py
tpds/schema/models/common/algo_1_0.py
tpds/schema/models/common/cert_def_1_0.py
tpds/schema/models/common/config_1_0.py
tpds/schema/models/common/data_1_0.py
tpds/schema/models/common/extension_1_0.py
tpds/schema/models/common/otp_1_0.py
tpds/schema/models/common/types.py
tpds/schema/models/ecc108_1_0/__init__.py
tpds/schema/models/ecc108_1_0/ecc108_config_1_0.py
tpds/schema/models/ecc204_1_0/__init__.py
tpds/schema/models/ecc204_1_0/ecc204_ta010_config_1_0.py
tpds/schema/models/ecc204_1_1/__init__.py
tpds/schema/models/ecc204_1_1/ecc204_ta010_config_1_1.py
tpds/schema/models/ecc204_1_2/__init__.py
tpds/schema/models/ecc204_1_2/ecc204_ta010_config_1_2.py
tpds/schema/models/ecc508_1_0/__init__.py
tpds/schema/models/ecc508_1_0/ecc508_config_1_0.py
tpds/schema/models/ecc608_1_0/__init__.py
tpds/schema/models/ecc608_1_0/ecc608_config_1_0.py
tpds/schema/models/sha104_1_0/__init__.py
tpds/schema/models/sha104_1_0/sha104_config_1_0.py
tpds/schema/models/sha105_1_0/__init__.py
tpds/schema/models/sha105_1_0/sha105_config_1_0.py
tpds/schema/models/sha204_1_0/__init__.py
tpds/schema/models/sha204_1_0/sha204_config_1_0.py
tpds_schema-1.2.0.dist-info/LICENSE
tpds_schema-1.2.0.dist-info/METADATA
tpds_schema-1.2.0.dist-info/WHEEL
tpds_schema-1.2.0.dist-info/top_level.txt
tpds_schema-1.2.0.dist-info/RECORD
